certbot_beget_plugin/__init__.py
certbot_beget_plugin/beget_plugin.py
certbot_beget_plugin-1.0.0.dev10.dist-info/LICENSE
certbot_beget_plugin-1.0.0.dev10.dist-info/METADATA
certbot_beget_plugin-1.0.0.dev10.dist-info/WHEEL
certbot_beget_plugin-1.0.0.dev10.dist-info/entry_points.txt
certbot_beget_plugin-1.0.0.dev10.dist-info/top_level.txt
certbot_beget_plugin-1.0.0.dev10.dist-info/RECORD
