Metadata-Version: 2.2
Name: certbot-beget-plugin
Version: 1.0.0.dev10
Summary: Beget DNS plugin for Certbot
Home-page: https://github.com/Medan-rfz/certbot-dns-beget-api/tree/1.0.0.dev10
Author: Medan-rfz
License: MIT License
License-File: LICENSE
Requires-Dist: certbot
Dynamic: author
Dynamic: description
Dynamic: description-content-type
Dynamic: home-page
Dynamic: license
Dynamic: requires-dist
Dynamic: summary
